tarp3_nuggets/__about__.py
tarp3_nuggets/__init__.py
tarp3_nuggets/change_it.py
tarp3_nuggets/drop_val.py
tarp3_nuggets/get_all_levels.py
tarp3_nuggets/have_seen.py
tarp3_nuggets/pvt_summary.py
tarp3_nuggets/taste.py
tarp3_nuggets-1.0.3.dist-info/METADATA
tarp3_nuggets-1.0.3.dist-info/WHEEL
tarp3_nuggets-1.0.3.dist-info/licenses/LICENSE.txt
tarp3_nuggets-1.0.3.dist-info/RECORD
