Metadata-Version: 2.4
Name: tarp3-nuggets
Version: 1.0.3
Summary: A package of nuggets found on the web
Author-email: "Anthony R. Plastino III" <anthony.r.plastino.iii@gmail.com>
License-Expression: MIT
License-File: LICENSE.txt
Classifier: Development Status :: 5 - Production/Stable
Classifier: Programming Language :: Python :: 3.13
Classifier: Programming Language :: Python :: Implementation :: PyPy
Requires-Python: >=3.13
